LICENSE
MANIFEST.in
README.md
requirements.txt
setup.py
docs/build/html/_sources/dpgbox.rst.txt
docs/build/html/_sources/dpgbox.theme.rst.txt
docs/build/html/_sources/index.rst.txt
docs/build/html/_sources/modules.rst.txt
docs/build/html/_sources/setup.rst.txt
docs/build/html/_static/file.png
docs/build/html/_static/minus.png
docs/build/html/_static/plus.png
docs/build/html/_static/css/fonts/fontawesome-webfont.ttf
docs/build/html/_static/fonts/Inconsolata-Bold.ttf
docs/build/html/_static/fonts/Inconsolata-Regular.ttf
docs/build/html/_static/fonts/Inconsolata.ttf
docs/build/html/_static/fonts/Lato-Bold.ttf
docs/build/html/_static/fonts/Lato-Regular.ttf
docs/build/html/_static/fonts/RobotoSlab-Bold.ttf
docs/build/html/_static/fonts/RobotoSlab-Regular.ttf
docs/build/html/_static/fonts/fontawesome-webfont.ttf
docs/build/html/_static/fonts/Lato/lato-bold.ttf
docs/build/html/_static/fonts/Lato/lato-bolditalic.ttf
docs/build/html/_static/fonts/Lato/lato-italic.ttf
docs/build/html/_static/fonts/Lato/lato-regular.ttf
docs/build/html/_static/fonts/RobotoSlab/roboto-slab-v7-bold.ttf
docs/build/html/_static/fonts/RobotoSlab/roboto-slab-v7-regular.ttf
docs/source/conf.py
docs/source/dpgbox.plot.rst
docs/source/dpgbox.rst
docs/source/dpgbox.theme.rst
docs/source/dpgbox.utils.rst
docs/source/index.rst
docs/source/modules.rst
docs/source/setup.rst
docs/source/_static/css/fonts/fontawesome-webfont.ttf
docs/source/_static/fonts/Inconsolata-Bold.ttf
docs/source/_static/fonts/Inconsolata-Regular.ttf
docs/source/_static/fonts/Inconsolata.ttf
docs/source/_static/fonts/Lato-Bold.ttf
docs/source/_static/fonts/Lato-Regular.ttf
docs/source/_static/fonts/RobotoSlab-Bold.ttf
docs/source/_static/fonts/RobotoSlab-Regular.ttf
docs/source/_static/fonts/fontawesome-webfont.ttf
docs/source/_static/fonts/Lato/lato-bold.ttf
docs/source/_static/fonts/Lato/lato-bolditalic.ttf
docs/source/_static/fonts/Lato/lato-italic.ttf
docs/source/_static/fonts/Lato/lato-regular.ttf
dpgbox.egg-info/PKG-INFO
dpgbox.egg-info/SOURCES.txt
dpgbox.egg-info/dependency_links.txt
dpgbox.egg-info/requires.txt
dpgbox.egg-info/top_level.txt
