Metadata-Version: 2.2
Name: dpgbox
Version: 1.1.0
Summary: DearPyGUI Library.
Home-page: https://iridescent.ink/dpgbox/
Download-URL: https://github.com/antsfamily/dpgbox/
Author: Zhi Liu
Author-email: zhiliu.mind@gmail.com
License: MIT
Keywords: DearPyGUI,Library,GUI,Toolbox
License-File: LICENSE
Requires-Dist: Cython
Requires-Dist: numpy
Requires-Dist: matplotlib
Requires-Dist: dearpygui
Requires-Dist: tqdm
Requires-Dist: lxml
Requires-Dist: pyyaml
Dynamic: author
Dynamic: author-email
Dynamic: description
Dynamic: download-url
Dynamic: home-page
Dynamic: keywords
Dynamic: license
Dynamic: requires-dist
Dynamic: summary
